HwCodecDetect/__init__.py
HwCodecDetect/install_ffmpeg_if_needed.py
HwCodecDetect/run_tests.py
HwCodecDetect/version.py
hwcodecdetect-0.1.8.dist-info/licenses/LICENSE
hwcodecdetect-0.1.8.dist-info/METADATA
hwcodecdetect-0.1.8.dist-info/WHEEL
hwcodecdetect-0.1.8.dist-info/entry_points.txt
hwcodecdetect-0.1.8.dist-info/top_level.txt
hwcodecdetect-0.1.8.dist-info/zip-safe
hwcodecdetect-0.1.8.dist-info/RECORD
