Metadata-Version: 2.4
Name: HwCodecDetect
Version: 0.1.8
Summary: A cross-platform tool to automatically detect and test hardware video decoders/encoders using FFmpeg.
Home-page: https://github.com/whyb/HwCodecDetect
Author: whyb
Author-email: whyb <whyber@outlook.com>
License-Expression: BSD-3-Clause
Project-URL: Homepage, https://github.com/whyb/HwCodecDetect
Project-URL: Issues, https://github.com/whyb/HwCodecDetect/issues
Classifier: Programming Language :: Python :: 3
Classifier: Operating System :: OS Independent
Classifier: Topic :: Multimedia :: Video
Classifier: Topic :: System :: Installation/Setup
Classifier: Topic :: Utilities
Requires-Python: >=3.8
License-File: LICENSE
Requires-Dist: colorama
Requires-Dist: tqdm
Requires-Dist: psutil
Dynamic: author
Dynamic: home-page
Dynamic: license-file
Dynamic: requires-python
